flytekitplugins_polars-1.16.12-py3.14-nspkg.pth
flytekitplugins/polars/__init__.py
flytekitplugins/polars/sd_transformers.py
flytekitplugins_polars-1.16.12.dist-info/METADATA
flytekitplugins_polars-1.16.12.dist-info/WHEEL
flytekitplugins_polars-1.16.12.dist-info/entry_points.txt
flytekitplugins_polars-1.16.12.dist-info/namespace_packages.txt
flytekitplugins_polars-1.16.12.dist-info/top_level.txt
flytekitplugins_polars-1.16.12.dist-info/RECORD
